booli/__init__.py
booli-0.1.0.dist-info/LICENSE
booli-0.1.0.dist-info/METADATA
booli-0.1.0.dist-info/WHEEL
booli-0.1.0.dist-info/top_level.txt
booli-0.1.0.dist-info/RECORD
