Metadata-Version: 2.1
Name: booli
Version: 0.1.0
Summary: Friendly wrapper for the Booli RESTful API endpoints
License: MIT
Classifier: Programming Language :: Python :: 3
Classifier: Programming Language :: Python :: 3.9
Classifier: Programming Language :: Python :: 3.10
Classifier: Programming Language :: Python :: 3.11
Requires-Python: >=3.9
License-File: LICENSE
